Metadata-Version: 2.2
Name: billybob_123
Version: 0.0.1
Summary: My Package
Author: Your Name
Author-email: vadimus.05ev@mail.ru
Dynamic: author
Dynamic: author-email
Dynamic: summary
